sharetop/__init__.py
sharetop/__version__.py
sharetop/api/__init__.py
sharetop/application/__init__.py
sharetop/application/base.py
sharetop/core/__init__.py
sharetop/core/cache.py
sharetop/core/config.py
sharetop/core/module_tools.py
sharetop/core/prepare.py
sharetop/core/utils.py
sharetop/core/bond/__init__.py
sharetop/core/bond/config.py
sharetop/core/bond/get_bond_info.py
sharetop/core/bond/get_bond_public_info.py
sharetop/core/bond_yield/__init__.py
sharetop/core/bond_yield/bond_yield_services.py
sharetop/core/bond_yield/config.py
sharetop/core/capital_flow/__init__.py
sharetop/core/capital_flow/capital_flow_monitor.py
sharetop/core/car/__init__.py
sharetop/core/car/car_detail.py
sharetop/core/car/car_services.py
sharetop/core/car/config.py
sharetop/core/common/__init__.py
sharetop/core/common/common_base.py
sharetop/core/common/config.py
sharetop/core/common/explain_change.py
sharetop/core/common/getter.py
sharetop/core/country/__init__.py
sharetop/core/country/config.py
sharetop/core/country/country_base_info.py
sharetop/core/fund/__init__.py
sharetop/core/fund/config.py
sharetop/core/fund/fund_list.py
sharetop/core/fund/fund_services.py
sharetop/core/fund/get_fund_base_info.py
sharetop/core/fund/get_fund_history_data.py
sharetop/core/fund/get_fund_industry_info.py
sharetop/core/fund/get_fund_invest_info.py
sharetop/core/fund/get_fund_rank.py
sharetop/core/fund/get_fund_real_time.py
sharetop/core/fund/get_period_change_info.py
sharetop/core/fund/get_types_percentage_info.py
sharetop/core/futures/__init__.py
sharetop/core/futures/get_futures_info.py
sharetop/core/index/__init__.py
sharetop/core/index/config.py
sharetop/core/index/logistics_index.py
sharetop/core/news/__init__.py
sharetop/core/news/config.py
sharetop/core/news/news_services.py
sharetop/core/oil/__init__.py
sharetop/core/oil/config.py
sharetop/core/oil/oil_detail.py
sharetop/core/pig/__init__.py
sharetop/core/pig/config.py
sharetop/core/pig/pig_detail.py
sharetop/core/pig/pig_services.py
sharetop-6.16.21.dist-info/LICENSE
sharetop-6.16.21.dist-info/METADATA
sharetop-6.16.21.dist-info/WHEEL
sharetop-6.16.21.dist-info/top_level.txt
sharetop-6.16.21.dist-info/RECORD
