Metadata-Version: 2.1
Name: sharetop
Version: 6.16.21
Summary: Provide data related to the economic market
Home-page: https://github.com/nrliangxy/sharetop
Author: nrliangxy
Author-email: nrliangxy@foxmail.com
License: MIT
Project-URL: Source, https://github.com/nrliangxy/sharetop
Keywords: data,finance,quant,stock,fund,futures,share
Platform: any
Classifier: License :: OSI Approved :: MIT License
Classifier: Programming Language :: Python :: 3.6
Classifier: Programming Language :: Python :: 3.7
Classifier: Programming Language :: Python :: 3.8
Classifier: Programming Language :: Python :: 3.9
Classifier: Programming Language :: Python :: 3.10
License-File: LICENSE
Requires-Dist: requests
Requires-Dist: rich
Requires-Dist: jsonpath
Requires-Dist: pandas
Requires-Dist: tqdm
Requires-Dist: retry
Requires-Dist: gevent
Requires-Dist: py-mini-racer
